chemvene/__init__.py
chemvene/chemvene.py
chemvene/misc.py
chemvene/pkg_files/imlup_gaia_v2_abrig_model_Tgas_SB_G04.txt
chemvene/read/__init__.py
chemvene/read/read_abunds.py
chemvene/read/read_lambda.py
chemvene/read/read_radfields.py
chemvene/read/read_rates.py
chemvene/test_files/rreacs_HHe.dat
chemvene/test_files/rspecies_HHe.dat
chemvene/test_files/uv_photons_small.dat
chemvene/test_files/xray_photons_small.dat
chemvene/test_files/environ/test/0io.inp
chemvene/test_files/environ/test/1environ.inp.e1.10.6547
chemvene/test_files/environ/test/1environ.inp.e1.20.0087
chemvene/test_files/environ/test/1environ.inp.e1.32.0981
chemvene/test_files/environ/test/1environ.inp.e1.43.9864
chemvene/test_files/test_model/0io.inp
chemvene/test_files/test_model/2times.inp
chemvene/test_files/test_model/3abunds.inp
chemvene/test_files/test_model/4toleran.inp
chemvene/test_files/test_model/5flags.inp
chemvene/test_files/test_model/6grainbe.inp
chemvene/test_files/test_model/7params.inp
chemvene/test_files/test_model/e1/r10.6547_e1_1.out
chemvene/test_files/test_model/e1/r10.6547_e1_10.out
chemvene/test_files/test_model/e1/r10.6547_e1_11.out
chemvene/test_files/test_model/e1/r10.6547_e1_12.out
chemvene/test_files/test_model/e1/r10.6547_e1_13.out
chemvene/test_files/test_model/e1/r10.6547_e1_14.out
chemvene/test_files/test_model/e1/r10.6547_e1_15.out
chemvene/test_files/test_model/e1/r10.6547_e1_16.out
chemvene/test_files/test_model/e1/r10.6547_e1_17.out
chemvene/test_files/test_model/e1/r10.6547_e1_18.out
chemvene/test_files/test_model/e1/r10.6547_e1_19.out
chemvene/test_files/test_model/e1/r10.6547_e1_2.out
chemvene/test_files/test_model/e1/r10.6547_e1_20.out
chemvene/test_files/test_model/e1/r10.6547_e1_21.out
chemvene/test_files/test_model/e1/r10.6547_e1_3.out
chemvene/test_files/test_model/e1/r10.6547_e1_4.out
chemvene/test_files/test_model/e1/r10.6547_e1_5.out
chemvene/test_files/test_model/e1/r10.6547_e1_6.out
chemvene/test_files/test_model/e1/r10.6547_e1_7.out
chemvene-1.1.dist-info/LICENSE
chemvene-1.1.dist-info/METADATA
chemvene-1.1.dist-info/WHEEL
chemvene-1.1.dist-info/top_level.txt
chemvene-1.1.dist-info/RECORD
