Metadata-Version: 2.1
Name: chemvene
Version: 1.1
Summary: A convenient chemical model visualization and analysis engine for processing output from the Michigan protoplanetary disk chemical modeling code.
Home-page: https://github.com/richardseifert/Chemvene
Author: Richard Seifert
Author-email: seifertricharda@gmail.com
License: MIT
Platform: UNKNOWN
Requires-Dist: matplotlib
Requires-Dist: numpy
Requires-Dist: pandas
Requires-Dist: scipy
